tptt/__init__.py
tptt/configuration_tptt.py
tptt/modeling_tptt.py
tptt/templates/home_card_template.md
tptt/templates/model_card_template.md
tptt/train_tptt.py
tptt-0.12.1.dist-info/LICENSE
tptt-0.12.1.dist-info/METADATA
tptt-0.12.1.dist-info/WHEEL
tptt-0.12.1.dist-info/RECORD
