Metadata-Version: 2.3
Name: tptt
Version: 0.12.1
Summary: TPTT : Transforming Pretrained Transformers into Titans
License: Apache-2.0
Author: fabienfrfr
Author-email: fabien.furfaro@gmail.com
Requires-Python: >=3.10
Classifier: License :: OSI Approved :: Apache Software License
Classifier: Programming Language :: Python :: 3
Classifier: Programming Language :: Python :: 3.10
Classifier: Programming Language :: Python :: 3.11
Classifier: Programming Language :: Python :: 3.12
Classifier: Programming Language :: Python :: 3.13
Requires-Dist: datasets
Requires-Dist: einops
Requires-Dist: ninja
Requires-Dist: peft
Requires-Dist: torch
Requires-Dist: transformers (>=4.45.0)
